LICENSE
MANIFEST.in
README.md
requirements.txt
setup.py
ab/__init__.py
ab/context_processors.py
ab/decorators.py
ab/settings.py
ab/utils.py
ab/templatetags/__init__.py
ab/templatetags/ab_tags.py
django_ab.egg-info/PKG-INFO
django_ab.egg-info/SOURCES.txt
django_ab.egg-info/dependency_links.txt
django_ab.egg-info/pbr.json
django_ab.egg-info/requires.txt
django_ab.egg-info/top_level.txt